{"cameraMode":{"drawMode":0,"name":"Shaded","section":"Shading Mode"},"sceneLighting":true,"audioPlay":false,"sceneViewState":{"showFog":true,"showMaterialUpdate":false,"showSkybox":true,"showFlares":true,"showImageEffects":true,"showParticleSystems":true},"in2DMode":false,"pivot":{"x":-29.860679626464845,"y":1.1138867139816285,"z":30.924991607666017},"rotation":{"x":0.007191494107246399,"y":0.38986366987228396,"z":-0.003044559620320797,"w":0.9208422303199768},"size":2.1051743030548097,"orthographic":false}